{
  "app": {
    "status": true,
    "redirect_url": ""
  },
  "drive": {
    "folder_id": "1ZkHoA3kWY_q4ZS5xcZ9m8AKpSa0x-am3",
    "api_key": "AIzaSyBF6nnzvXFUWuLKw-kgmIKH7aaK8NNMJba"
  },
  "settings": {
    "more_apps_url": "https://play.solodroid.co.id/store/apps/",
    "privacy_policy_url": "https://sites.google.com/view/walldrive-privacy-policy",
    "terms_conditions_url": "https://sites.google.com/view/walldrive-terms-conditions",
    "email_help_feedback": "help.solodroid@gmail.com",
    "show_wallpaper_name": true,
	"show_full_screen_wallpaper_details": false,
    "enable_center_crop_wallpaper_details": true,
    "enable_exit_dialog": true,
    "enable_rtl_mode": false,
    "enable_dark_mode_as_default_theme": false
  },
  "ads": {
    "status": true,
    "main_ads": "admob",
    "backup_ads": "facebook",
    "ads_unit_id": {
      "admob": {
        "publisher_id": "pub-3940256099942544",
        "app_open_id": "ca-app-pub-3940256099942544/3419835294",
        "banner_id": "ca-app-pub-3940256099942544/6300978111",
        "interstitial_id": "ca-app-pub-3940256099942544/1033173712",
        "rewarded_id": "ca-app-pub-3940256099942544/5224354917",
        "native_id": "ca-app-pub-3940256099942544/2247696110"
      },
      "google_ad_manager": {
        "app_open_id": "/6499/example/app-open",
        "banner_id": "/6499/example/banner",
        "interstitial_id": "/6499/example/interstitial",
        "rewarded_id": "/6499/example/rewarded",
        "native_id": "/6499/example/native"
      },
      "facebook": {
        "banner_id": "YOUR_PLACEMENT_ID",
        "interstitial_id": "YOUR_PLACEMENT_ID",
        "rewarded_id": "YOUR_PLACEMENT_ID",
        "native_id": "YOUR_PLACEMENT_ID"
      },
      "applovin_max": {
        "app_open_id": "0",
        "banner_id": "0",
        "interstitial_id": "0",
        "rewarded_id": "0",
        "native_id": "0"
      },
      "applovin_discovery": {
        "banner_zone_id": "0",
        "mrec_zone_id": "0",
        "rewarded_zone_id": "0",
        "interstitial_zone_id": "0"
      },
      "startapp": {
        "app_id": "0"
      },
      "unity": {
        "game_id": "4089993",
        "banner_id": "banner",
        "interstitial_id": "video",
        "rewarded_id": "rewardedVideo"
      },
      "ironsource": {
        "app_key": "85460dcd",
        "banner_id": "DefaultBanner",
        "interstitial_id": "DefaultInterstitial",
        "rewarded_id": "DefaultRewardedVideo"
      },
      "wortise": {
        "app_id": "test-app-id",
        "app_open_id": "test-app-open",
        "banner_id": "test-banner",
        "interstitial_id": "test-interstitial",
        "rewarded_id": "test-rewarded",
        "native_id": "test-native"
      }
    },
    "placement": {
      "banner_home": true,
      "banner_wallpaper_details": true,
      "banner_favorite": true,
      "interstitial_wallpaper_list": true,
      "rewarded_wallpaper_details": true,
      "native_wallpaper_list": true,
      "native_exit_dialog": true,
      "app_open_ad_on_start": true,
      "app_open_ad_on_resume": true
    },
    "global": {
      "interstitial_ad_interval": 3,
      "native_ad_index_2_columns": 4,
      "native_ad_index_3_columns": 6,
      "native_ad_style_exit_dialog": "medium",
      "native_ad_style_wallpaper_list": "large",
      "native_ad_style_wallpaper_details": "large"
    }
  }
}